quanguru/__init__.py
quanguru/simUnits.py
quanguru/QuantumToolbox/Hamiltonians.py
quanguru/QuantumToolbox/IPR.py
quanguru/QuantumToolbox/__init__.py
quanguru/QuantumToolbox/_helpers.py
quanguru/QuantumToolbox/basicGates.py
quanguru/QuantumToolbox/customTypes.py
quanguru/QuantumToolbox/eigenVecVal.py
quanguru/QuantumToolbox/evolution.py
quanguru/QuantumToolbox/functions.py
quanguru/QuantumToolbox/linearAlgebra.py
quanguru/QuantumToolbox/operators.py
quanguru/QuantumToolbox/quasiProbabilities.py
quanguru/QuantumToolbox/rmtDistributions.py
quanguru/QuantumToolbox/spinRotations.py
quanguru/QuantumToolbox/states.py
quanguru/QuantumToolbox/thermodynamics.py
quanguru/classes/QDrive.py
quanguru/classes/QGates.py
quanguru/classes/QPro.py
quanguru/classes/QProtocol.py
quanguru/classes/QRes.py
quanguru/classes/QSim.py
quanguru/classes/QSimBase.py
quanguru/classes/QSimComp.py
quanguru/classes/QSweep.py
quanguru/classes/QSys.py
quanguru/classes/QSystem.py
quanguru/classes/QTerms.py
quanguru/classes/__init__.py
quanguru/classes/base.py
quanguru/classes/baseClasses.py
quanguru/classes/environment.py
quanguru/classes/exceptions.py
quanguru/classes/modularSweep.py
quanguru/classes/tempConfig.py
quanguru/classes/extensions/__init__.py
quanguru/classes/extensions/couplings.py
quanguru/extensions/__init__.py
quanguru/extensions/_helpers.py
quanguru/extensions/saveReadCSV.py
quanguru/extensions/saveReadHFive.py
QuanGuru-0.0.1rc19.dist-info/LICENSE
QuanGuru-0.0.1rc19.dist-info/METADATA
QuanGuru-0.0.1rc19.dist-info/WHEEL
QuanGuru-0.0.1rc19.dist-info/top_level.txt
QuanGuru-0.0.1rc19.dist-info/RECORD
