Metadata-Version: 2.1
Name: QuanGuru
Version: 0.0.1rc19
Summary: QuanGuru (pronounced Kangaroo) is a Python library for numerical modelling of Quantum systems.
Home-page: https://github.com/CirQuS-UTS/QuanGuru
Author: CirQuS Team: Cahit Kargi, Fabio Henriques, Angsar Manatuly, Adrien Di Lonardo, Giorge Gemisis, Juan Pablo Dehollain, and Nathan K. Langford
Author-email: ckargi88@gmail.com
License: BSD 3-Clause License
Project-URL: Documentation, https://cirqus-uts.github.io/QuanGuru/
Project-URL: Source Code, https://github.com/CirQuS-UTS/QuanGuru
Project-URL: Bug Tracker, https://github.com/CirQuS-UTS/QuanGuru
Keywords: quantum,physics,simulation
Classifier: Programming Language :: Python :: 3 :: Only
Classifier: Programming Language :: Python :: 3.6
Classifier: Programming Language :: Python :: 3.7
Classifier: Programming Language :: Python :: 3.8
Classifier: Programming Language :: Python :: 3.9
Classifier: License :: OSI Approved :: BSD License
Classifier: Intended Audience :: Science/Research
Classifier: Topic :: Scientific/Engineering
Classifier: Operating System :: OS Independent
Requires-Python: >=3.5
License-File: LICENSE
Requires-Dist: numpy
Requires-Dist: scipy
